MLibrary/__init__.py
MLibrary/knn.py
MLibrary/myfunctions.py
MLibrary/regressions.py
MLibrary/utils.py
MLibrary-0.1.1.dist-info/LICENSE
MLibrary-0.1.1.dist-info/METADATA
MLibrary-0.1.1.dist-info/WHEEL
MLibrary-0.1.1.dist-info/top_level.txt
MLibrary-0.1.1.dist-info/RECORD
